Workbook

Sheet MVS - Forecasts
A2: MVS Motors Ltd
A3: XYZ Motors Limited, incorporated in 1982, is the listed company of the XYZ Group in India .
A4: XYZ Motors Limited, is a leading player in the Indian automobile industry and the global leader in middleweight motorcycles.
A5: The Company has manufacturing facilities across the country and sells primarily in India.
A6: XYZ has a joint venture with Sweden’s AB Volvo to create Volvo XYZ Commercial Vehicles Limited (VECV).
A7: VECV is engaged in truck and bus operations, auto components business, and technical consulting services business.
A9: Particulars | B9: FY19 | C9: FY20 | D9: FY21 | E9: FY22 | F9: FY23 | G9: FY24 | H9: FY25 | K9: Particulars | L9: FY26P | M9: FY27P | N9: FY28P | O9: FY29P | P9: FY30P
A10: Revenue | B10: 20160 | C10: 18849 | D10: 19421 | E10: 24355 | F10: 31974 | G10: 39145 | H10: 44089 | K10: Revenue | L10: =H10*(1.165) -> 51363.685 | M10: =L10*1.168 -> 59992.784 | N10: =M10*1.158 -> 69471.644 | O10: =N10*1.155 -> 80239.749 | P10: =O10*1.152 -> 92436.191
A11: % growth | C11: =C10/B10-1 -> -0.065029762 | D11: =D10/C10-1 -> 0.030346437 | E11: =E10/D10-1 -> 0.25405489 | F11: =F10/E10-1 -> 0.31283104 | G11: =G10/F10-1 -> 0.22427597 | H11: =H10/G10-1 -> 0.12629966 | I11: =AVERAGE(C11:H11) -> 0.14712971 | K11: % growth | L11: =L10/H10-1 -> 0.165 | M11: =M10/L10-1 -> 0.168 | N11: =N10/M10-1 -> 0.158 | O11: =O10/N10-1 -> 0.155 | P11: =P10/O10-1 -> 0.152
A13: Operating Margin | B13: 2163 | C13: 2264 | D13: 2232 | E13: 2755 | F13: 4027 | G13: 5500 | H13: 6575
A14: % growth | C14: =C13/B13-1 -> 0.046694406 | D14: =D13/C13-1 -> -0.014134276 | E14: =E13/D13-1 -> 0.234319 | F14: =F13/E13-1 -> 0.46170599 | G14: =G13/F13-1 -> 0.36578098 | H14: =H13/G13-1 -> 0.19545455 | I14: =AVERAGE(C14:H14) -> 0.21497011
A15: % margin | B15: =B13/B10 -> 0.10729167 | C15: =C13/C10 -> 0.12011247 | D15: =D13/D10 -> 0.11492714 | E15: =E13/E10 -> 0.11311846 | F15: =F13/F10 -> 0.12594608 | G15: =G13/G10 -> 0.14050326 | H15: =H13/H10 -> 0.14913017 | I15: =AVERAGE(C15:H15) -> 0.1272896
A17: Net Margin | B17: 704.67 | C17: 624.62 | D17: 594.26 | E17: 756.82 | F17: 1328.67 | G17: 1686.37 | H17: 2235.56
A18: % growth | C18: =C17/B17-1 -> -0.11359927 | D18: =D17/C17-1 -> -0.048605552 | E18: =E17/D17-1 -> 0.2735503 | F18: =F17/E17-1 -> 0.75559578 | G18: =G17/F17-1 -> 0.26921659 | H18: =H17/G17-1 -> 0.325664 | I18: =AVERAGE(C18:H18) -> 0.24363697
A19: % margin | B19: =B17/B10 -> 0.034953869 | C19: =C17/C10 -> 0.033138098 | D19: =D17/D10 -> 0.030598836 | E19: =E17/E10 -> 0.031074523 | F19: =F17/F10 -> 0.041554701 | G19: =G17/G10 -> 0.043080087 | H19: =H17/H10 -> 0.050705618 | I19: =AVERAGE(C19:H19) -> 0.038358644
A21: FCFE | C21: ='MVS - Calculation of FCFE'!E48 -> 7316.43 | D21: ='MVS - Calculation of FCFE'!F48 -> 7908.47 | E21: ='MVS - Calculation of FCFE'!G48 -> 10653.95 | F21: ='MVS - Calculation of FCFE'!H48 -> 14567.33 | G21: ='MVS - Calculation of FCFE'!I48 -> 20245.21 | H21: ='MVS - Calculation of FCFE'!J48 -> 26478.36 | K21: FCFE | L21: =L10*51.2% -> 26298.207 | M21: =L21*(1.254) -> 32977.951 | N21: =M21*(1.261) -> 41585.196 | O21: =N21*1.269 -> 52771.614 | P21: =O21*1.271 -> 67072.722
A22: % growth | D22: =D21/C21-1 -> 0.080919246 | E22: =E21/D21-1 -> 0.34715691 | F22: =F21/E21-1 -> 0.36731729 | G22: =G21/E21-1 -> 0.9002539 | H22: =H21/F21-1 -> 0.81765361 | I22: =AVERAGE(C22:H22) -> 0.50266019 | K22: % growth | L22: =L21/H21-1 -> -0.006803793 | M22: =M21/L21-1 -> 0.254 | N22: =N21/M21-1 -> 0.261 | O22: =O21/N21-1 -> 0.269 | P22: =P21/O21-1 -> 0.271
A23: % margin | B23: =B21/B10 -> 0 | C23: =C21/C10 -> 0.38816011 | D23: =D21/D10 -> 0.4072123 | E23: =E21/E10 -> 0.43744406 | F23: =F21/F10 -> 0.45559924 | G23: =G21/G10 -> 0.51718508 | H23: =H21/H10 -> 0.60056613 | I23: =AVERAGE(C23:H23) -> 0.46769449 | K23: % margin | L23: =L21/L10 -> 0.512 | M23: =M21/M10 -> 0.54969863 | N23: =N21/N10 -> 0.59859238 | O23: =O21/O10 -> 0.65767422 | P23: =P21/P10 -> 0.72561106

Sheet MVS - Valuation
A2: MVS Motors Ltd
A3: XYZ Motors Limited, incorporated in 1982, is the listed company of the XYZ Group in India .
A4: XYZ Motors Limited, is a leading player in the Indian automobile industry and the global leader in middleweight motorcycles.
A5: The Company has manufacturing facilities across the country and sells primarily in India.
A6: XYZ has a joint venture with Sweden’s AB Volvo to create Volvo XYZ Commercial Vehicles Limited (VECV).
A7: VECV is engaged in truck and bus operations, auto components business, and technical consulting services business.
A9: Perpetual Growth | C9: 0.07
A10: Rate of Discount | C10: 0.1432
A11: CF (t-1) - CF5 | C11: =D19 -> 67072.722
A12: Terminal Value | C12: =C11*(1+C9)/(C10-C9) -> 980434.6
A14: Year | B14: Year No. | C14: CF | D14: Cash Flows | E14: Growth Rate | F14: Discounting Factor | G14: CF0
A15: 46112 | B15: 1 | C15: CF1 | D15: ='MVS - Forecasts'!L21 -> 26298.207 | F15: =1/(1+$B$24)^B15 -> 0.87473758 | G15: =D15*F15 -> 23004.03
A16: =EOMONTH(A15,12) -> 46477 | B16: =B15+1 -> 2 | C16: CF2 | D16: ='MVS - Forecasts'!M21 -> 32977.951 | E16: =D16/D15-1 -> 0.254 | F16: =1/(1+$B$24)^B16 -> 0.76516583 | G16: =D16*F16 -> 25233.601
A17: =EOMONTH(A16,12) -> 46843 | B17: 3 | C17: CF3 | D17: ='MVS - Forecasts'!N21 -> 41585.196 | E17: =D17/D16-1 -> 0.261 | F17: =1/(1+$B$24)^B17 -> 0.66931931 | G17: =D17*F17 -> 27833.775
A18: =EOMONTH(A17,12) -> 47208 | B18: =B17+1 -> 4 | C18: CF4 | D18: ='MVS - Forecasts'!O21 -> 52771.614 | E18: =D18/D17-1 -> 0.269 | F18: =1/(1+$B$24)^B18 -> 0.58547875 | G18: =D18*F18 -> 30896.659
A19: =EOMONTH(A18,12) -> 47573 | B19: =B18+1 -> 5 | C19: CF5 | D19: ='MVS - Forecasts'!P21 -> 67072.722 | E19: =D19/D18-1 -> 0.271 | F19: =1/(1+$B$24)^B19 -> 0.51214026 | G19: =D19*F19 -> 34350.641
A20: =EOMONTH(A19,12) -> 47938 | B20: =B19+1 -> 6 | C20: Terminal Value | D20: =C12 -> 980434.6 | E20: 0.07 | F20: =1/(1+$B$24)^B20 -> 0.44798833 | G20: =D20*F20 -> 439223.26
G21: =SUM(G15:G20) -> 580541.97
A24: Rate of return (Cost of equity) | B24: 0.1432
A25: (The Calculation for the Cost of Equity is given in XYZ Motors - Cost of Equity Sheet)
A27: Current Market Value as per DCF | B27: =G21 -> 580541.97 | C27: Cr
A28: Today at 25th June 2025, XYZ Motors Ltd operates at a market cap of 1.37LCr. Hence, the company might be significantly overvalued.
A30: Current Market Share Price | B30: 137000 | C30: Cr
A31: Outstanding Shares of XYZ Co | B31: 273768554

Sheet MVS - Calculation of FCFE
A2: XYZ Motors Ltd
A4: Free Cash Flow to Equity:
A5: FCFE is a metric of how much cash can be distributed to the equity shareholders of the company as dividends or stock buybacks.
A6: Dividends and Stock Buybacks are distributed after all expenses, reinvestments, and debt repayments are taken care of.
A8: The formula to calculate the Free Cash Flow to Equity (FCFE) is the following:
A10: Cash Flow from Operations
A11: (-) Capital Expenditure
A12: (+) Net Debt Issued
A13: Free Cash Flow to Equity (FCFE)
A15: The formula for Capital Expenditure is the following:
A17: (+) Closing PPE
A18: (-) Opening PPE | C18: Net Increase/Decrease in PPE
C19: (+) Depreciation
C20: Capital Expenditue
A22: The formula for Net Debt Issued is the following:
A24: (Short Term Debt + Long Term Debt) - Liquid Investment
A25: Net Debt Issued
A27: The Calculation for YoY Free Cash Flow Equity (FCFE)
A29: YoY | B29: Capital Expenditure
D30: 20 | E30: 21 | F30: 22 | G30: 23 | H30: 24 | I30: 25
B31: Closing PPE | D31: =4485+217+115 -> 4817 | E31: =4818+240+129 -> 5187 | F31: =5542+284+151 -> 5977 | G31: =5411+311+171 -> 5893 | H31: =5683+359+238 -> 6280 | I31: 5488
B32: Opening PPE | D32: =-(4126+191+105) -> -4422 | E32: =-D31 -> -4817 | F32: =-E31 -> -5187 | G32: =-F31 -> -5977 | H32: =-G31 -> -5893 | I32: =-H31 -> -6280
B33: Depreciation | D33: 556 | E33: 564.82 | F33: 742.86 | G33: 858.86 | H33: 975.12 | I33: 1045.56
D34: =SUM(D31:D33) -> 951 | E34: =E31+E32+E33 -> 934.82 | F34: =SUM(F31:F33) -> 1532.86 | G34: =SUM(G31:G33) -> 774.86 | H34: =SUM(H31:H33) -> 1362.12 | I34: =SUM(I31:I33) -> 253.56
A36: YoY | B36: Net Debt Issued
D37: 20 | E37: 21 | F37: 22 | G37: 23 | H37: 24 | I37: 25
B38: Long Term Debt | D38: 5221 | E38: 6280 | F38: 7306 | G38: 9064 | H38: 12629 | I38: 13932
B39: Short Term Debt | D39: 3781 | E39: 3069 | F39: 7992 | G39: 12562 | H39: 12657 | I39: 13683
B40: Liquid Investment | D40: 1108 | E40: 1657 | F40: 1536 | G40: 1879 | H40: 2426 | I40: 4386
D41: =(D38+D39)-D40 -> 7894 | E41: =(E38+E39)-E40 -> 7692 | F41: =(F38+F39)-F40 -> 13762 | G41: =(G38+G39)-G40 -> 19747 | H41: =(H38+H39)-H40 -> 22860 | I41: =(I38+I39)-I40 -> 23229
A43: YoY | B43: Free Cash Flow to Equity
E44: 20 | F44: 21 | G44: 22 | H44: 23 | I44: 24 | J44: 25
B45: Cash from Operations | E45: 373.43 | F45: 1151.29 | G45: -1575.19 | H45: -4404.81 | I45: -1252.67 | J45: 3502.92
B46: Capital Expenditure | E46: =-D34 -> -951 | F46: =-E34 -> -934.82 | G46: =-F34 -> -1532.86 | H46: =-G34 -> -774.86 | I46: =-H34 -> -1362.12 | J46: =-I34 -> -253.56
B47: Net Debt Issued | E47: =D41 -> 7894 | F47: =E41 -> 7692 | G47: =F41 -> 13762 | H47: =G41 -> 19747 | I47: =H41 -> 22860 | J47: =I41 -> 23229
E48: =SUM(E45:E47) -> 7316.43 | F48: =SUM(F45:F47) -> 7908.47 | G48: =SUM(G45:G47) -> 10653.95 | H48: =SUM(H45:H47) -> 14567.33 | I48: =SUM(I45:I47) -> 20245.21 | J48: =SUM(J45:J47) -> 26478.36

Sheet MVS - Cost of Equity
A2: XYZ Motors Ltd
A4: We will be using the Capital Asset Pricing Model (CAPM) to derive the Cost of Equity.
A5: The Formula for CAPM:
B7: Ke | C7: Rf + β* (Erm - Rf)
B9: Ke | C9: Cost of Equity
B10: Rf | C10: Risk Free Rate of Return
B11: β | C11: Beta
B12: Erm | C12: Estimated Return on Investment
B13: (Erm - Rf) | C13: Market Risk Premium
B15: The Risk Free Rate of Return is the 10 Year Bond rate that can be also called as Treasury Yield is 7% as taken from the market.
B16: The Beta Factor of XYZ Motors Ltd is 0.59 (5Y Monthly)
B17: The Estimated return on Investment is 13.9% as per the historical CAGR of 5 years.
B19: Steps to Calculate the Ke (Return on Equity Required):
B21: Step 1 | C21: Calculate the Market Risk Premium
C22: We will simply subtract 13.05% (the estimated return on Investment) with 7% (the Risk Free Rate of Return)
C23: 13.05%-7% | D23: =13.05%-7% -> 0.0605
B25: Step 2 | C25: Multiply the Market Risk Premium with the β (Beta Factor)
C26: 6.05%*1.21 | D26: =6.05%*1.21 -> 0.073205
B28: Step 3 | C28: The final step would be totalling and deriving the Required Rate of Return on Equity
C29: 0.07+0.073205 | D29: =0.07+0.073205 -> 0.143205 | E29: or 14.3205%
B31: Overall Calculation
B33: Ke | C33: Rf + β* (Erm - Rf)
C34: 0.07+1.21*(0.0605)
C35: =0.07+(1.21*(0.0605)) -> 0.143205 | D35: or 14.32%
